whatsappguru/__init__.py
whatsappguru/whatsapp.py
whatsappguru-0.3.1.dist-info/METADATA
whatsappguru-0.3.1.dist-info/WHEEL
whatsappguru-0.3.1.dist-info/top_level.txt
whatsappguru-0.3.1.dist-info/RECORD
