Metadata-Version: 2.1
Name: whatsappguru
Version: 0.3.1
Summary: The package contains the tools to analyze your WhatsApp chats
Home-page: https://github.com/lollococce/whatsappguru
Author: Lorenzo Coacci
Author-email: lorenzo@coacci.com
License: MIT
Platform: UNKNOWN
Classifier: Programming Language :: Python :: 3
Classifier: License :: OSI Approved :: MIT License
Classifier: Natural Language :: English
Requires-Dist: pandas
Requires-Dist: emoji
Requires-Dist: alive-progress
Requires-Dist: uuid
Requires-Dist: iago
